{
  "count": 90,
  "tasks": [
    {
      "id": "78458",
      "rawText": "Каталог задач\nКаталог заданий по Русский язык\nДощинский-2025 (50 вар.)\nТема №3. Задания по маленькому тексту\n08 Дощинский-2025 (50 вар.)\nКаталог задач\nКаталог вариантов\nКонструктор вариантов\n01. Вспоминай формулы\nпо каждой теме\n02. Решай новые задачи\nкаждый день\n03. Вдумчиво разбирай\nрешения\n04. Готовиться с платформой\nШколково - ЛЕГКО!\nПолучи персональную скидку на курсы подготовки к экзаменам\n\nХочу получить огромную скидку\n\nПодтемы раздела №3. задания по маленькому тексту\nРешаем задачи\n\nКонтент к задаче:\n\nЧеловеческое общение, по данным исследователей, на две трети состоит из речевого (вербального, словесного) общения: именно при помощи речи чаще всего происходит общение между людьми. Контактируя с другими людьми, человек совершает речевые действия. Таким образом, общение есть деятельность, в рамках которой осуществляется сложная речевая деятельность. Она предшествует другим видам деятельности, сопровождает их, то есть составляет основу любой другой деятельности человека: производственной, коммерческой, финансовой, научной, управленческой. Так, например, образование, обучение, пропаганда знаний немыслимы без общения посредством речи. Иначе говоря, особенность речевой деятельности заключается в том, что она всегда включается в более широкую систему деятельности как необходимый компонент.\n\nОвладение искусством общения необходимо для каждого человека независимо от того, каким видом деятельности он занимается <…> будет заниматься. Люди в процессе выполнения профессиональной деятельности обязаны что-либо обсуждать, выслушивать, записывать, составлять документы, задавать вопросы и отвечать на них. От того, насколько умело осуществляется речевая деятельность, зависит успех любой профессиональной деятельности. Деловые переговоры будут неэффективны, а личное бытовое общение тягостным, если, нарушая элементарные правила общения, участники коммуникации перебивают собеседника, проявляют нежелание считаться с его мнением, равнодушны, невнимательны к его проблемам, многословны и говорят не по существу.\n\n \n\n(По А.А. Евтюгиной)\n\nЗадача 1#78458Максимум баллов за задание: 1\n\nУкажите варианты ответов, в которых даны верные характеристики фрагмента текста. Запишите номера ответов.\n\n \n\n1) Наряду с общеупотребительной лексикой в тексте используются термины (общение, речевая деятельность и др.).\n\n2) Использование эпитетов («необходимый компонент», «бытовое общение»), метафор (зависит успех, переговоры будут неэффективны) способствует эмоциональности, выразительности изложения, помогает передать авторскую мысль о необходимости соблюдать правила речевого общения.\n\n3) В тексте используются отглагольные существительные (исследователей, образование, обучение), глаголы несовершенного вида (состоит, происходит, совершает).\n\n4) Синтаксис текста разнообразен: наряду с простыми предложениями, осложнёнными или вводной конструкцией, или однородными членами, или обособленными членами, автор использует разные типы сложных предложений.\n\n5) Текст относится к официально-деловому стил"
    },
    {
      "id": "78458",
      "rawText": "Каталог задач\nКаталог заданий по Русский язык\nДощинский-2025 (50 вар.)\nТема №3. Задания по маленькому тексту\n08 Дощинский-2025 (50 вар.)\nКаталог задач\nКаталог вариантов\nКонструктор вариантов\n01. Вспоминай формулы\nпо каждой теме\n02. Решай новые задачи\nкаждый день\n03. Вдумчиво разбирай\nрешения\n04. Готовиться с платформой\nШколково - ЛЕГКО!\nПолучи персональную скидку на курсы подготовки к экзаменам\n\nХочу получить огромную скидку\n\nПодтемы раздела №3. задания по маленькому тексту\nРешаем задачи\n\nКонтент к задаче:\n\nЧеловеческое общение, по данным исследователей, на две трети состоит из речевого (вербального, словесного) общения: именно при помощи речи чаще всего происходит общение между людьми. Контактируя с другими людьми, человек совершает речевые действия. Таким образом, общение есть деятельность, в рамках которой осуществляется сложная речевая деятельность. Она предшествует другим видам деятельности, сопровождает их, то есть составляет основу любой другой деятельности человека: производственной, коммерческой, финансовой, научной, управленческой. Так, например, образование, обучение, пропаганда знаний немыслимы без общения посредством речи. Иначе говоря, особенность речевой деятельности заключается в том, что она всегда включается в более широкую систему деятельности как необходимый компонент.\n\nОвладение искусством общения необходимо для каждого человека независимо от того, каким видом деятельности он занимается <…> будет заниматься. Люди в процессе выполнения профессиональной деятельности обязаны что-либо обсуждать, выслушивать, записывать, составлять документы, задавать вопросы и отвечать на них. От того, насколько умело осуществляется речевая деятельность, зависит успех любой профессиональной деятельности. Деловые переговоры будут неэффективны, а личное бытовое общение тягостным, если, нарушая элементарные правила общения, участники коммуникации перебивают собеседника, проявляют нежелание считаться с его мнением, равнодушны, невнимательны к его проблемам, многословны и говорят не по существу.\n\n \n\n(По А.А. Евтюгиной)\n\nЗадача 1#78458Максимум баллов за задание: 1\n\nУкажите варианты ответов, в которых даны верные характеристики фрагмента текста. Запишите номера ответов.\n\n \n\n1) Наряду с общеупотребительной лексикой в тексте используются термины (общение, речевая деятельность и др.).\n\n2) Использование эпитетов («необходимый компонент», «бытовое общение»), метафор (зависит успех, переговоры будут неэффективны) способствует эмоциональности, выразительности изложения, помогает передать авторскую мысль о необходимости соблюдать правила речевого общения.\n\n3) В тексте используются отглагольные существительные (исследователей, образование, обучение), глаголы несовершенного вида (состоит, происходит, совершает).\n\n4) Синтаксис текста разнообразен: наряду с простыми предложениями, осложнёнными или вводной конструкцией, или однородными членами, или обособленными членами, автор использует разные типы сложных предложений.\n\n5) Текст относится к официально-деловому стил"
    },
    {
      "id": "78458",
      "rawText": "Каталог задач\nКаталог заданий по Русский язык\nДощинский-2025 (50 вар.)\nТема №3. Задания по маленькому тексту\n08 Дощинский-2025 (50 вар.)\nКаталог задач\nКаталог вариантов\nКонструктор вариантов\n01. Вспоминай формулы\nпо каждой теме\n02. Решай новые задачи\nкаждый день\n03. Вдумчиво разбирай\nрешения\n04. Готовиться с платформой\nШколково - ЛЕГКО!\nПолучи персональную скидку на курсы подготовки к экзаменам\n\nХочу получить огромную скидку\n\nПодтемы раздела №3. задания по маленькому тексту\nРешаем задачи\n\nКонтент к задаче:\n\nЧеловеческое общение, по данным исследователей, на две трети состоит из речевого (вербального, словесного) общения: именно при помощи речи чаще всего происходит общение между людьми. Контактируя с другими людьми, человек совершает речевые действия. Таким образом, общение есть деятельность, в рамках которой осуществляется сложная речевая деятельность. Она предшествует другим видам деятельности, сопровождает их, то есть составляет основу любой другой деятельности человека: производственной, коммерческой, финансовой, научной, управленческой. Так, например, образование, обучение, пропаганда знаний немыслимы без общения посредством речи. Иначе говоря, особенность речевой деятельности заключается в том, что она всегда включается в более широкую систему деятельности как необходимый компонент.\n\nОвладение искусством общения необходимо для каждого человека независимо от того, каким видом деятельности он занимается <…> будет заниматься. Люди в процессе выполнения профессиональной деятельности обязаны что-либо обсуждать, выслушивать, записывать, составлять документы, задавать вопросы и отвечать на них. От того, насколько умело осуществляется речевая деятельность, зависит успех любой профессиональной деятельности. Деловые переговоры будут неэффективны, а личное бытовое общение тягостным, если, нарушая элементарные правила общения, участники коммуникации перебивают собеседника, проявляют нежелание считаться с его мнением, равнодушны, невнимательны к его проблемам, многословны и говорят не по существу.\n\n \n\n(По А.А. Евтюгиной)\n\nЗадача 1#78458Максимум баллов за задание: 1\n\nУкажите варианты ответов, в которых даны верные характеристики фрагмента текста. Запишите номера ответов.\n\n \n\n1) Наряду с общеупотребительной лексикой в тексте используются термины (общение, речевая деятельность и др.).\n\n2) Использование эпитетов («необходимый компонент», «бытовое общение»), метафор (зависит успех, переговоры будут неэффективны) способствует эмоциональности, выразительности изложения, помогает передать авторскую мысль о необходимости соблюдать правила речевого общения.\n\n3) В тексте используются отглагольные существительные (исследователей, образование, обучение), глаголы несовершенного вида (состоит, происходит, совершает).\n\n4) Синтаксис текста разнообразен: наряду с простыми предложениями, осложнёнными или вводной конструкцией, или однородными членами, или обособленными членами, автор использует разные типы сложных предложений.\n\n5) Текст относится к официально-деловому стил"
    },
    {
      "id": "78458",
      "rawText": "Каталог задач\nКаталог заданий по Русский язык\nДощинский-2025 (50 вар.)\nТема №3. Задания по маленькому тексту\n08 Дощинский-2025 (50 вар.)\nКаталог задач\nКаталог вариантов\nКонструктор вариантов\n01. Вспоминай формулы\nпо каждой теме\n02. Решай новые задачи\nкаждый день\n03. Вдумчиво разбирай\nрешения\n04. Готовиться с платформой\nШколково - ЛЕГКО!\nПолучи персональную скидку на курсы подготовки к экзаменам\n\nХочу получить огромную скидку\n\nПодтемы раздела №3. задания по маленькому тексту\nРешаем задачи\n\nКонтент к задаче:\n\nЧеловеческое общение, по данным исследователей, на две трети состоит из речевого (вербального, словесного) общения: именно при помощи речи чаще всего происходит общение между людьми. Контактируя с другими людьми, человек совершает речевые действия. Таким образом, общение есть деятельность, в рамках которой осуществляется сложная речевая деятельность. Она предшествует другим видам деятельности, сопровождает их, то есть составляет основу любой другой деятельности человека: производственной, коммерческой, финансовой, научной, управленческой. Так, например, образование, обучение, пропаганда знаний немыслимы без общения посредством речи. Иначе говоря, особенность речевой деятельности заключается в том, что она всегда включается в более широкую систему деятельности как необходимый компонент.\n\nОвладение искусством общения необходимо для каждого человека независимо от того, каким видом деятельности он занимается <…> будет заниматься. Люди в процессе выполнения профессиональной деятельности обязаны что-либо обсуждать, выслушивать, записывать, составлять документы, задавать вопросы и отвечать на них. От того, насколько умело осуществляется речевая деятельность, зависит успех любой профессиональной деятельности. Деловые переговоры будут неэффективны, а личное бытовое общение тягостным, если, нарушая элементарные правила общения, участники коммуникации перебивают собеседника, проявляют нежелание считаться с его мнением, равнодушны, невнимательны к его проблемам, многословны и говорят не по существу.\n\n \n\n(По А.А. Евтюгиной)\n\nЗадача 1#78458Максимум баллов за задание: 1\n\nУкажите варианты ответов, в которых даны верные характеристики фрагмента текста. Запишите номера ответов.\n\n \n\n1) Наряду с общеупотребительной лексикой в тексте используются термины (общение, речевая деятельность и др.).\n\n2) Использование эпитетов («необходимый компонент», «бытовое общение»), метафор (зависит успех, переговоры будут неэффективны) способствует эмоциональности, выразительности изложения, помогает передать авторскую мысль о необходимости соблюдать правила речевого общения.\n\n3) В тексте используются отглагольные существительные (исследователей, образование, обучение), глаголы несовершенного вида (состоит, происходит, совершает).\n\n4) Синтаксис текста разнообразен: наряду с простыми предложениями, осложнёнными или вводной конструкцией, или однородными членами, или обособленными членами, автор использует разные типы сложных предложений.\n\n5) Текст относится к официально-деловому стил"
    },
    {
      "id": "78458",
      "rawText": "Каталог задач\nКаталог заданий по Русский язык\nДощинский-2025 (50 вар.)\nТема №3. Задания по маленькому тексту\n08 Дощинский-2025 (50 вар.)\nКаталог задач\nКаталог вариантов\nКонструктор вариантов\n01. Вспоминай формулы\nпо каждой теме\n02. Решай новые задачи\nкаждый день\n03. Вдумчиво разбирай\nрешения\n04. Готовиться с платформой\nШколково - ЛЕГКО!\nПолучи персональную скидку на курсы подготовки к экзаменам\n\nХочу получить огромную скидку\n\nПодтемы раздела №3. задания по маленькому тексту\nРешаем задачи\n\nКонтент к задаче:\n\nЧеловеческое общение, по данным исследователей, на две трети состоит из речевого (вербального, словесного) общения: именно при помощи речи чаще всего происходит общение между людьми. Контактируя с другими людьми, человек совершает речевые действия. Таким образом, общение есть деятельность, в рамках которой осуществляется сложная речевая деятельность. Она предшествует другим видам деятельности, сопровождает их, то есть составляет основу любой другой деятельности человека: производственной, коммерческой, финансовой, научной, управленческой. Так, например, образование, обучение, пропаганда знаний немыслимы без общения посредством речи. Иначе говоря, особенность речевой деятельности заключается в том, что она всегда включается в более широкую систему деятельности как необходимый компонент.\n\nОвладение искусством общения необходимо для каждого человека независимо от того, каким видом деятельности он занимается <…> будет заниматься. Люди в процессе выполнения профессиональной деятельности обязаны что-либо обсуждать, выслушивать, записывать, составлять документы, задавать вопросы и отвечать на них. От того, насколько умело осуществляется речевая деятельность, зависит успех любой профессиональной деятельности. Деловые переговоры будут неэффективны, а личное бытовое общение тягостным, если, нарушая элементарные правила общения, участники коммуникации перебивают собеседника, проявляют нежелание считаться с его мнением, равнодушны, невнимательны к его проблемам, многословны и говорят не по существу.\n\n \n\n(По А.А. Евтюгиной)\n\nЗадача 1#78458Максимум баллов за задание: 1\n\nУкажите варианты ответов, в которых даны верные характеристики фрагмента текста. Запишите номера ответов.\n\n \n\n1) Наряду с общеупотребительной лексикой в тексте используются термины (общение, речевая деятельность и др.).\n\n2) Использование эпитетов («необходимый компонент», «бытовое общение»), метафор (зависит успех, переговоры будут неэффективны) способствует эмоциональности, выразительности изложения, помогает передать авторскую мысль о необходимости соблюдать правила речевого общения.\n\n3) В тексте используются отглагольные существительные (исследователей, образование, обучение), глаголы несовершенного вида (состоит, происходит, совершает).\n\n4) Синтаксис текста разнообразен: наряду с простыми предложениями, осложнёнными или вводной конструкцией, или однородными членами, или обособленными членами, автор использует разные типы сложных предложений.\n\n5) Текст относится к официально-деловому стил"
    },
    {
      "id": "78458",
      "rawText": "Подтемы раздела №3. задания по маленькому тексту\nРешаем задачи\n\nКонтент к задаче:\n\nЧеловеческое общение, по данным исследователей, на две трети состоит из речевого (вербального, словесного) общения: именно при помощи речи чаще всего происходит общение между людьми. Контактируя с другими людьми, человек совершает речевые действия. Таким образом, общение есть деятельность, в рамках которой осуществляется сложная речевая деятельность. Она предшествует другим видам деятельности, сопровождает их, то есть составляет основу любой другой деятельности человека: производственной, коммерческой, финансовой, научной, управленческой. Так, например, образование, обучение, пропаганда знаний немыслимы без общения посредством речи. Иначе говоря, особенность речевой деятельности заключается в том, что она всегда включается в более широкую систему деятельности как необходимый компонент.\n\nОвладение искусством общения необходимо для каждого человека независимо от того, каким видом деятельности он занимается <…> будет заниматься. Люди в процессе выполнения профессиональной деятельности обязаны что-либо обсуждать, выслушивать, записывать, составлять документы, задавать вопросы и отвечать на них. От того, насколько умело осуществляется речевая деятельность, зависит успех любой профессиональной деятельности. Деловые переговоры будут неэффективны, а личное бытовое общение тягостным, если, нарушая элементарные правила общения, участники коммуникации перебивают собеседника, проявляют нежелание считаться с его мнением, равнодушны, невнимательны к его проблемам, многословны и говорят не по существу.\n\n \n\n(По А.А. Евтюгиной)\n\nЗадача 1#78458Максимум баллов за задание: 1\n\nУкажите варианты ответов, в которых даны верные характеристики фрагмента текста. Запишите номера ответов.\n\n \n\n1) Наряду с общеупотребительной лексикой в тексте используются термины (общение, речевая деятельность и др.).\n\n2) Использование эпитетов («необходимый компонент», «бытовое общение»), метафор (зависит успех, переговоры будут неэффективны) способствует эмоциональности, выразительности изложения, помогает передать авторскую мысль о необходимости соблюдать правила речевого общения.\n\n3) В тексте используются отглагольные существительные (исследователей, образование, обучение), глаголы несовершенного вида (состоит, происходит, совершает).\n\n4) Синтаксис текста разнообразен: наряду с простыми предложениями, осложнёнными или вводной конструкцией, или однородными членами, или обособленными членами, автор использует разные типы сложных предложений.\n\n5) Текст относится к официально-деловому стилю, так как основная цель автора – дать инструкцию о том, как осуществлять речевую деятельность.\n\n(Взято из сборника Дощинского-2025, 50 вар. (вар. 28))\n\nСообщить об ошибке\nОтвет и решение\n\nНаборы\n\nКомбо-тарифы сразу по нескольким предметам\n\nКонтент к задаче:\n\nКультура речи – понятие многозначное. Одна из основных задач культуры речи – это охрана литературного языка, его норм. Следует подчеркнуть, что такая охрана является дело"
    },
    {
      "id": "78458",
      "rawText": "Подтемы раздела №3. задания по маленькому тексту\nРешаем задачи\n\nКонтент к задаче:\n\nЧеловеческое общение, по данным исследователей, на две трети состоит из речевого (вербального, словесного) общения: именно при помощи речи чаще всего происходит общение между людьми. Контактируя с другими людьми, человек совершает речевые действия. Таким образом, общение есть деятельность, в рамках которой осуществляется сложная речевая деятельность. Она предшествует другим видам деятельности, сопровождает их, то есть составляет основу любой другой деятельности человека: производственной, коммерческой, финансовой, научной, управленческой. Так, например, образование, обучение, пропаганда знаний немыслимы без общения посредством речи. Иначе говоря, особенность речевой деятельности заключается в том, что она всегда включается в более широкую систему деятельности как необходимый компонент.\n\nОвладение искусством общения необходимо для каждого человека независимо от того, каким видом деятельности он занимается <…> будет заниматься. Люди в процессе выполнения профессиональной деятельности обязаны что-либо обсуждать, выслушивать, записывать, составлять документы, задавать вопросы и отвечать на них. От того, насколько умело осуществляется речевая деятельность, зависит успех любой профессиональной деятельности. Деловые переговоры будут неэффективны, а личное бытовое общение тягостным, если, нарушая элементарные правила общения, участники коммуникации перебивают собеседника, проявляют нежелание считаться с его мнением, равнодушны, невнимательны к его проблемам, многословны и говорят не по существу.\n\n \n\n(По А.А. Евтюгиной)\n\nЗадача 1#78458Максимум баллов за задание: 1\n\nУкажите варианты ответов, в которых даны верные характеристики фрагмента текста. Запишите номера ответов.\n\n \n\n1) Наряду с общеупотребительной лексикой в тексте используются термины (общение, речевая деятельность и др.).\n\n2) Использование эпитетов («необходимый компонент», «бытовое общение»), метафор (зависит успех, переговоры будут неэффективны) способствует эмоциональности, выразительности изложения, помогает передать авторскую мысль о необходимости соблюдать правила речевого общения.\n\n3) В тексте используются отглагольные существительные (исследователей, образование, обучение), глаголы несовершенного вида (состоит, происходит, совершает).\n\n4) Синтаксис текста разнообразен: наряду с простыми предложениями, осложнёнными или вводной конструкцией, или однородными членами, или обособленными членами, автор использует разные типы сложных предложений.\n\n5) Текст относится к официально-деловому стилю, так как основная цель автора – дать инструкцию о том, как осуществлять речевую деятельность.\n\n(Взято из сборника Дощинского-2025, 50 вар. (вар. 28))\n\nСообщить об ошибке\nОтвет и решение\n\nНаборы\n\nКомбо-тарифы сразу по нескольким предметам\n\nКонтент к задаче:\n\nКультура речи – понятие многозначное. Одна из основных задач культуры речи – это охрана литературного языка, его норм. Следует подчеркнуть, что такая охрана является дело"
    },
    {
      "id": "78458",
      "rawText": "Решаем задачи\n\nКонтент к задаче:\n\nЧеловеческое общение, по данным исследователей, на две трети состоит из речевого (вербального, словесного) общения: именно при помощи речи чаще всего происходит общение между людьми. Контактируя с другими людьми, человек совершает речевые действия. Таким образом, общение есть деятельность, в рамках которой осуществляется сложная речевая деятельность. Она предшествует другим видам деятельности, сопровождает их, то есть составляет основу любой другой деятельности человека: производственной, коммерческой, финансовой, научной, управленческой. Так, например, образование, обучение, пропаганда знаний немыслимы без общения посредством речи. Иначе говоря, особенность речевой деятельности заключается в том, что она всегда включается в более широкую систему деятельности как необходимый компонент.\n\nОвладение искусством общения необходимо для каждого человека независимо от того, каким видом деятельности он занимается <…> будет заниматься. Люди в процессе выполнения профессиональной деятельности обязаны что-либо обсуждать, выслушивать, записывать, составлять документы, задавать вопросы и отвечать на них. От того, насколько умело осуществляется речевая деятельность, зависит успех любой профессиональной деятельности. Деловые переговоры будут неэффективны, а личное бытовое общение тягостным, если, нарушая элементарные правила общения, участники коммуникации перебивают собеседника, проявляют нежелание считаться с его мнением, равнодушны, невнимательны к его проблемам, многословны и говорят не по существу.\n\n \n\n(По А.А. Евтюгиной)\n\nЗадача 1#78458Максимум баллов за задание: 1\n\nУкажите варианты ответов, в которых даны верные характеристики фрагмента текста. Запишите номера ответов.\n\n \n\n1) Наряду с общеупотребительной лексикой в тексте используются термины (общение, речевая деятельность и др.).\n\n2) Использование эпитетов («необходимый компонент», «бытовое общение»), метафор (зависит успех, переговоры будут неэффективны) способствует эмоциональности, выразительности изложения, помогает передать авторскую мысль о необходимости соблюдать правила речевого общения.\n\n3) В тексте используются отглагольные существительные (исследователей, образование, обучение), глаголы несовершенного вида (состоит, происходит, совершает).\n\n4) Синтаксис текста разнообразен: наряду с простыми предложениями, осложнёнными или вводной конструкцией, или однородными членами, или обособленными членами, автор использует разные типы сложных предложений.\n\n5) Текст относится к официально-деловому стилю, так как основная цель автора – дать инструкцию о том, как осуществлять речевую деятельность.\n\n(Взято из сборника Дощинского-2025, 50 вар. (вар. 28))\n\nСообщить об ошибке\nОтвет и решение\n\nНаборы\n\nКомбо-тарифы сразу по нескольким предметам\n\nКонтент к задаче:\n\nКультура речи – понятие многозначное. Одна из основных задач культуры речи – это охрана литературного языка, его норм. Следует подчеркнуть, что такая охрана является делом национальной важности, поскольку литературный я"
    },
    {
      "id": "78458",
      "rawText": "Решаем задачи\n\nКонтент к задаче:\n\nЧеловеческое общение, по данным исследователей, на две трети состоит из речевого (вербального, словесного) общения: именно при помощи речи чаще всего происходит общение между людьми. Контактируя с другими людьми, человек совершает речевые действия. Таким образом, общение есть деятельность, в рамках которой осуществляется сложная речевая деятельность. Она предшествует другим видам деятельности, сопровождает их, то есть составляет основу любой другой деятельности человека: производственной, коммерческой, финансовой, научной, управленческой. Так, например, образование, обучение, пропаганда знаний немыслимы без общения посредством речи. Иначе говоря, особенность речевой деятельности заключается в том, что она всегда включается в более широкую систему деятельности как необходимый компонент.\n\nОвладение искусством общения необходимо для каждого человека независимо от того, каким видом деятельности он занимается <…> будет заниматься. Люди в процессе выполнения профессиональной деятельности обязаны что-либо обсуждать, выслушивать, записывать, составлять документы, задавать вопросы и отвечать на них. От того, насколько умело осуществляется речевая деятельность, зависит успех любой профессиональной деятельности. Деловые переговоры будут неэффективны, а личное бытовое общение тягостным, если, нарушая элементарные правила общения, участники коммуникации перебивают собеседника, проявляют нежелание считаться с его мнением, равнодушны, невнимательны к его проблемам, многословны и говорят не по существу.\n\n \n\n(По А.А. Евтюгиной)\n\nЗадача 1#78458Максимум баллов за задание: 1\n\nУкажите варианты ответов, в которых даны верные характеристики фрагмента текста. Запишите номера ответов.\n\n \n\n1) Наряду с общеупотребительной лексикой в тексте используются термины (общение, речевая деятельность и др.).\n\n2) Использование эпитетов («необходимый компонент», «бытовое общение»), метафор (зависит успех, переговоры будут неэффективны) способствует эмоциональности, выразительности изложения, помогает передать авторскую мысль о необходимости соблюдать правила речевого общения.\n\n3) В тексте используются отглагольные существительные (исследователей, образование, обучение), глаголы несовершенного вида (состоит, происходит, совершает).\n\n4) Синтаксис текста разнообразен: наряду с простыми предложениями, осложнёнными или вводной конструкцией, или однородными членами, или обособленными членами, автор использует разные типы сложных предложений.\n\n5) Текст относится к официально-деловому стилю, так как основная цель автора – дать инструкцию о том, как осуществлять речевую деятельность.\n\n(Взято из сборника Дощинского-2025, 50 вар. (вар. 28))\n\nСообщить об ошибке\nОтвет и решение\n\nНаборы\n\nКомбо-тарифы сразу по нескольким предметам\n\nКонтент к задаче:\n\nКультура речи – понятие многозначное. Одна из основных задач культуры речи – это охрана литературного языка, его норм. Следует подчеркнуть, что такая охрана является делом национальной важности, поскольку литературный я"
    },
    {
      "id": "78458",
      "rawText": "Контент к задаче:\n\nЧеловеческое общение, по данным исследователей, на две трети состоит из речевого (вербального, словесного) общения: именно при помощи речи чаще всего происходит общение между людьми. Контактируя с другими людьми, человек совершает речевые действия. Таким образом, общение есть деятельность, в рамках которой осуществляется сложная речевая деятельность. Она предшествует другим видам деятельности, сопровождает их, то есть составляет основу любой другой деятельности человека: производственной, коммерческой, финансовой, научной, управленческой. Так, например, образование, обучение, пропаганда знаний немыслимы без общения посредством речи. Иначе говоря, особенность речевой деятельности заключается в том, что она всегда включается в более широкую систему деятельности как необходимый компонент.\n\nОвладение искусством общения необходимо для каждого человека независимо от того, каким видом деятельности он занимается <…> будет заниматься. Люди в процессе выполнения профессиональной деятельности обязаны что-либо обсуждать, выслушивать, записывать, составлять документы, задавать вопросы и отвечать на них. От того, насколько умело осуществляется речевая деятельность, зависит успех любой профессиональной деятельности. Деловые переговоры будут неэффективны, а личное бытовое общение тягостным, если, нарушая элементарные правила общения, участники коммуникации перебивают собеседника, проявляют нежелание считаться с его мнением, равнодушны, невнимательны к его проблемам, многословны и говорят не по существу.\n\n \n\n(По А.А. Евтюгиной)\n\nЗадача 1#78458Максимум баллов за задание: 1\n\nУкажите варианты ответов, в которых даны верные характеристики фрагмента текста. Запишите номера ответов.\n\n \n\n1) Наряду с общеупотребительной лексикой в тексте используются термины (общение, речевая деятельность и др.).\n\n2) Использование эпитетов («необходимый компонент», «бытовое общение»), метафор (зависит успех, переговоры будут неэффективны) способствует эмоциональности, выразительности изложения, помогает передать авторскую мысль о необходимости соблюдать правила речевого общения.\n\n3) В тексте используются отглагольные существительные (исследователей, образование, обучение), глаголы несовершенного вида (состоит, происходит, совершает).\n\n4) Синтаксис текста разнообразен: наряду с простыми предложениями, осложнёнными или вводной конструкцией, или однородными членами, или обособленными членами, автор использует разные типы сложных предложений.\n\n5) Текст относится к официально-деловому стилю, так как основная цель автора – дать инструкцию о том, как осуществлять речевую деятельность.\n\n(Взято из сборника Дощинского-2025, 50 вар. (вар. 28))\n\nСообщить об ошибке\nОтвет и решение\n\nНаборы\n\nКомбо-тарифы сразу по нескольким предметам\n\nКонтент к задаче:\n\nКультура речи – понятие многозначное. Одна из основных задач культуры речи – это охрана литературного языка, его норм. Следует подчеркнуть, что такая охрана является делом национальной важности, поскольку литературный язык – это именн"
    },
    {
      "id": "78458",
      "rawText": "Задача 1#78458Максимум баллов за задание: 1\n\nУкажите варианты ответов, в которых даны верные характеристики фрагмента текста. Запишите номера ответов.\n\n \n\n1) Наряду с общеупотребительной лексикой в тексте используются термины (общение, речевая деятельность и др.).\n\n2) Использование эпитетов («необходимый компонент», «бытовое общение»), метафор (зависит успех, переговоры будут неэффективны) способствует эмоциональности, выразительности изложения, помогает передать авторскую мысль о необходимости соблюдать правила речевого общения.\n\n3) В тексте используются отглагольные существительные (исследователей, образование, обучение), глаголы несовершенного вида (состоит, происходит, совершает).\n\n4) Синтаксис текста разнообразен: наряду с простыми предложениями, осложнёнными или вводной конструкцией, или однородными членами, или обособленными членами, автор использует разные типы сложных предложений.\n\n5) Текст относится к официально-деловому стилю, так как основная цель автора – дать инструкцию о том, как осуществлять речевую деятельность.\n\n(Взято из сборника Дощинского-2025, 50 вар. (вар. 28))\n\nСообщить об ошибке\nОтвет и решение"
    },
    {
      "id": "78458",
      "rawText": "Задача 1#78458Максимум баллов за задание: 1\n\nУкажите варианты ответов, в которых даны верные характеристики фрагмента текста. Запишите номера ответов.\n\n \n\n1) Наряду с общеупотребительной лексикой в тексте используются термины (общение, речевая деятельность и др.).\n\n2) Использование эпитетов («необходимый компонент», «бытовое общение»), метафор (зависит успех, переговоры будут неэффективны) способствует эмоциональности, выразительности изложения, помогает передать авторскую мысль о необходимости соблюдать правила речевого общения.\n\n3) В тексте используются отглагольные существительные (исследователей, образование, обучение), глаголы несовершенного вида (состоит, происходит, совершает).\n\n4) Синтаксис текста разнообразен: наряду с простыми предложениями, осложнёнными или вводной конструкцией, или однородными членами, или обособленными членами, автор использует разные типы сложных предложений.\n\n5) Текст относится к официально-деловому стилю, так как основная цель автора – дать инструкцию о том, как осуществлять речевую деятельность.\n\n(Взято из сборника Дощинского-2025, 50 вар. (вар. 28))"
    },
    {
      "id": "78458",
      "rawText": "Задача 1#78458Максимум баллов за задание: 1"
    },
    {
      "id": "78458",
      "rawText": "Задача 1#78458Максимум баллов за задание: 1"
    },
    {
      "id": "78463",
      "rawText": "Задача 2#78463Максимум баллов за задание: 1\n\nУкажите варианты ответов, в которых даны верные характеристики фрагмента текста. Запишите номера ответов.\n\n \n\n1) Наряду с общеупотребительной лексикой в тексте используются термины (культура речи, лексики, диалекты и др).\n\n2) Использование эпитетов («национальной важности», «культурная часть общества»)способствует эмоциональности, выразительности изложения, помогает понять, что такое культура речи.\n\n3) В тексте используются отглагольные существительные (создание, развития, становление), глаголы несовершенного вида (появиться, сумел).\n\n4) На синтаксическом уровне логичность и последовательность изложения достигаются за счёт использования вводных слов и конструкций, простых предложений с однородными членами, сложноподчинённых предложений.\n\n5) Текст относится к научному стилю, так как основная его цель – сообщение точной научной информации о культуре речи и её задачах.\n\n(Взято из сборника Дощинского-2025, 50 вар. (вар. 31))\n\nСообщить об ошибке\nОтвет и решение"
    }
  ]
}